{
  "Groceries": [
    "migros",
    "migrolino",
    "coop", 
    "aldi", 
    "lidl", 
    "denner", 
    "supermarkt", 
    "lebensmittel",
    "edeka",
    "m express",
    "pronto",
    "avec"
  ],
  "Dining": [
    "restaurant", 
    "café", 
    "bistro", 
    "imbiss", 
    "pizzeria", 
    "coffee", 
    "kaffee", 
    "mcdonalds", 
    "burger king", 
    "starbucks", 
    "subway",
    "gastro",
    "hiltl"
  ],
  "Shopping": [
    "shopping", 
    "kaufhaus", 
    "kleidung", 
    "mode", 
    "elektronik", 
    "media markt", 
    "saturn", 
    "amazon", 
    "zalando", 
    "h&m", 
    "zara"
  ],
  "Transit": [
    "bahn", 
    "zug", 
    "bus", 
    "tram", 
    "taxi",
    "verkehr", 
    "mobility",
    "sbb",
    "db vertrieb",
    "benzin",
    "tankstelle",
    "vbz"
  ],
  "Entertainment": [
    "kino", 
    "cinema", 
    "theater", 
    "konzert", 
    "festival", 
    "spotify", 
    "netflix", 
    "disney", 
    "prime", 
    "hbo"
  ],
  "Bills & Fees": [
    "gebühr", 
    "fee", 
    "steuer", 
    "versicherung", 
    "miete", 
    "internet", 
    "telefon", 
    "swisscom", 
    "sunrise",
    "krankenkasse",
    "suva",
    "linuxfoundation",
    "dr. med."
  ],
  "Travel": [
    "hotel", 
    "flug", 
    "flight", 
    "reise", 
    "booking", 
    "airbnb", 
    "expedia", 
    "hostel",
    "sixt",
    "europcar",
    "sncf"
  ],
  "Income": [
    "lohn", 
    "salary", 
    "gehalt", 
    "einkommen", 
    "vergütung", 
    "bonus", 
    "dividende",
    "spesen",
    "wise"
  ]
} 